stannum/__init__.py
stannum/auxiliary.py
stannum/tin.py
stannum/tube.py
stannum/utils.py
stannum-0.9.1.dist-info/LICENSE
stannum-0.9.1.dist-info/METADATA
stannum-0.9.1.dist-info/WHEEL
stannum-0.9.1.dist-info/top_level.txt
stannum-0.9.1.dist-info/RECORD
