Metadata-Version: 2.1
Name: stannum
Version: 0.9.1
Summary: Fusing Taichi into PyTorch
Home-page: https://github.com/ifsheldon/stannum
Author: Feng Liang
Author-email: feng.liang@kaust.edu.sa
Project-URL: Bug Tracker, https://github.com/ifsheldon/stannum/issues
Classifier: Programming Language :: Python :: 3
Classifier: License :: OSI Approved :: MIT License
Classifier: Operating System :: OS Independent
Requires-Python: >=3.6
License-File: LICENSE
